okta_ai_sdk/__init__.py
okta_ai_sdk/connected_accounts/__init__.py
okta_ai_sdk/connected_accounts/client.py
okta_ai_sdk/connected_accounts/types.py
okta_ai_sdk/core/__init__.py
okta_ai_sdk/core/sdk.py
okta_ai_sdk/cross_app_access/__init__.py
okta_ai_sdk/cross_app_access/client.py
okta_ai_sdk/token_exchange/client.py
okta_ai_sdk/types/__init__.py
okta_ai_sdk/types/core.py
okta_ai_sdk/types/cross_app_access.py
okta_ai_sdk/types/token_exchange.py
okta_ai_sdk_proto-1.0.3.dist-info/licenses/LICENSE
okta_ai_sdk_proto-1.0.3.dist-info/METADATA
okta_ai_sdk_proto-1.0.3.dist-info/WHEEL
okta_ai_sdk_proto-1.0.3.dist-info/top_level.txt
okta_ai_sdk_proto-1.0.3.dist-info/RECORD
