Metadata-Version: 2.4
Name: okta-ai-sdk-proto
Version: 1.0.3
Summary: Comprehensive Okta SDK for AI applications with Token Exchange, Cross-App Access (ID-JAG), and Connected Accounts support
Home-page: https://github.com/okta/okta-ai-sdk-proto
Author: Okta Inc.
Author-email: "Okta Inc." <developers@okta.com>
License: MIT
Project-URL: Homepage, https://github.com/okta/okta-ai-sdk-proto
Project-URL: Repository, https://github.com/okta/okta-ai-sdk-proto
Project-URL: Documentation, https://github.com/okta/okta-ai-sdk-proto#readme
Project-URL: Bug Tracker, https://github.com/okta/okta-ai-sdk-proto/issues
Keywords: okta,ai,token-exchange,cross-app-access,id-jag,oauth,jwt,authentication,authorization,langraph
Classifier: Development Status :: 3 - Alpha
Classifier: Intended Audience :: Developers
Classifier: License :: OSI Approved :: MIT License
Classifier: Programming Language :: Python :: 3
Classifier: Programming Language :: Python :: 3.8
Classifier: Programming Language :: Python :: 3.9
Classifier: Programming Language :: Python :: 3.10
Classifier: Programming Language :: Python :: 3.11
Classifier: Programming Language :: Python :: 3.12
Classifier: Topic :: Software Development :: Libraries :: Python Modules
Classifier: Topic :: Internet :: WWW/HTTP :: Dynamic Content
Classifier: Topic :: Security
Requires-Python: >=3.8
License-File: LICENSE
Requires-Dist: requests>=2.28.0
Requires-Dist: PyJWT>=2.6.0
Requires-Dist: cryptography>=3.4.8
Requires-Dist: pydantic>=1.10.0
Provides-Extra: dev
Requires-Dist: pytest>=7.0.0; extra == "dev"
Requires-Dist: pytest-asyncio>=0.21.0; extra == "dev"
Requires-Dist: pytest-cov>=4.0.0; extra == "dev"
Requires-Dist: black>=22.0.0; extra == "dev"
Requires-Dist: isort>=5.10.0; extra == "dev"
Requires-Dist: mypy>=1.0.0; extra == "dev"
Requires-Dist: flake8>=5.0.0; extra == "dev"
Provides-Extra: test
Requires-Dist: pytest>=7.0.0; extra == "test"
Requires-Dist: pytest-asyncio>=0.21.0; extra == "test"
Requires-Dist: pytest-cov>=4.0.0; extra == "test"
Requires-Dist: httpx>=0.24.0; extra == "test"
Dynamic: author
Dynamic: home-page
Dynamic: license-file
Dynamic: requires-python
